[
    {
        "id": 0,
        "latitude": 22.5491013631,
        "longitude": 114.07851184,
        "speed": 0,
        "driven_time": 43,
        "driven_distance": 123.115949227,
        "avg_speed": 2.86316160992,
        "all_stop_times": 1,
        "all_waiting_time": 30,
        "all_waiting_time/driven_time": 0.697674418605,
        "in_road_time": 43,
        "in_road_distance": 123.115949227,
        "in_road_stop_times": 1,
        "in_road_waiting_time": 30
    },
    {
        "id": 1,
        "latitude": 22.5473181181,
        "longitude": 114.087855029,
        "speed": 16.67,
        "driven_time": 43,
        "driven_distance": 630.400562796,
        "avg_speed": 14.6604782046,
        "all_stop_times": 0,
        "all_waiting_time": 0,
        "all_waiting_time/driven_time": 0,
        "in_road_time": 13,
        "in_road_distance": 204.55404567,
        "in_road_stop_times": 0,
        "in_road_waiting_time": 0
    },
    {
        "id": 2,
        "latitude": 22.5501037005,
        "longitude": 114.077414714,
        "speed": 16.67,
        "driven_time": 43,
        "driven_distance": 259.952861867,
        "avg_speed": 6.04541539226,
        "all_stop_times": 1,
        "all_waiting_time": 18,
        "all_waiting_time/driven_time": 0.418604651163,
        "in_road_time": 2,
        "in_road_distance": 33.34,
        "in_road_stop_times": 0,
        "in_road_waiting_time": 0
    },
    {
        "id": 3,
        "latitude": 22.5490396971,
        "longitude": 114.078412154,
        "speed": 11.67,
        "driven_time": 43,
        "driven_distance": 461.106995661,
        "avg_speed": 10.7234185038,
        "all_stop_times": 1,
        "all_waiting_time": 5,
        "all_waiting_time/driven_time": 0.116279069767,
        "in_road_time": 1,
        "in_road_distance": 11.67,
        "in_road_stop_times": 0,
        "in_road_waiting_time": 0
    },
    {
        "id": 4,
        "latitude": 22.5439139046,
        "longitude": 114.08788907,
        "speed": 16.67,
        "driven_time": 41,
        "driven_distance": 449.128595735,
        "avg_speed": 10.9543559935,
        "all_stop_times": 1,
        "all_waiting_time": 4,
        "all_waiting_time/driven_time": 0.0975609756098,
        "in_road_time": 13,
        "in_road_distance": 155.35,
        "in_road_stop_times": 0,
        "in_road_waiting_time": 0
    },
    {
        "id": 5,
        "latitude": 22.5469710259,
        "longitude": 114.076238377,
        "speed": 0,
        "driven_time": 39,
        "driven_distance": 168.242303678,
        "avg_speed": 4.31390522252,
        "all_stop_times": 1,
        "all_waiting_time": 24,
        "all_waiting_time/driven_time": 0.615384615385,
        "in_road_time": 39,
        "in_road_distance": 168.242303678,
        "in_road_stop_times": 1,
        "in_road_waiting_time": 24
    },
    {
        "id": 6,
        "latitude": 22.5455103645,
        "longitude": 114.082663414,
        "speed": 0,
        "driven_time": 39,
        "driven_distance": 259.449459781,
        "avg_speed": 6.6525502508,
        "all_stop_times": 1,
        "all_waiting_time": 18,
        "all_waiting_time/driven_time": 0.461538461538,
        "in_road_time": 39,
        "in_road_distance": 259.449459781,
        "in_road_stop_times": 1,
        "in_road_waiting_time": 18
    },
    {
        "id": 7,
        "latitude": 22.5492788213,
        "longitude": 114.082993379,
        "speed": 16.67,
        "driven_time": 39,
        "driven_distance": 540.876517126,
        "avg_speed": 13.8686286443,
        "all_stop_times": 0,
        "all_waiting_time": 0,
        "all_waiting_time/driven_time": 0,
        "in_road_time": 9,
        "in_road_distance": 115.03,
        "in_road_stop_times": 0,
        "in_road_waiting_time": 0
    },
    {
        "id": 8,
        "latitude": 22.5490442505,
        "longitude": 114.079559767,
        "speed": 11.67,
        "driven_time": 38,
        "driven_distance": 260.529927143,
        "avg_speed": 6.85605071429,
        "all_stop_times": 1,
        "all_waiting_time": 13,
        "all_waiting_time/driven_time": 0.342105263158,
        "in_road_time": 1,
        "in_road_distance": 11.67,
        "in_road_stop_times": 0,
        "in_road_waiting_time": 0
    },
    {
        "id": 9,
        "latitude": 22.5476990656,
        "longitude": 114.091046941,
        "speed": 16.67,
        "driven_time": 38,
        "driven_distance": 387.689620303,
        "avg_speed": 10.202358429,
        "all_stop_times": 1,
        "all_waiting_time": 6,
        "all_waiting_time/driven_time": 0.157894736842,
        "in_road_time": 13,
        "in_road_distance": 155.35,
        "in_road_stop_times": 0,
        "in_road_waiting_time": 0
    },
    {
        "id": 10,
        "latitude": 22.5454998798,
        "longitude": 114.087981933,
        "speed": 0,
        "driven_time": 37,
        "driven_distance": 355.887970411,
        "avg_speed": 9.61859379488,
        "all_stop_times": 1,
        "all_waiting_time": 11,
        "all_waiting_time/driven_time": 0.297297297297,
        "in_road_time": 36.8242834199,
        "in_road_distance": 355.887970411,
        "in_road_stop_times": 1,
        "in_road_waiting_time": 11
    },
    {
        "id": 11,
        "latitude": 22.5455910256,
        "longitude": 114.079155511,
        "speed": 16.67,
        "driven_time": 37,
        "driven_distance": 439.230725047,
        "avg_speed": 11.8711006769,
        "all_stop_times": 1,
        "all_waiting_time": 1,
        "all_waiting_time/driven_time": 0.027027027027,
        "in_road_time": 13,
        "in_road_distance": 155.35,
        "in_road_stop_times": 0,
        "in_road_waiting_time": 0
    },
    {
        "id": 12,
        "latitude": 22.5515090727,
        "longitude": 114.078854825,
        "speed": 16.67,
        "driven_time": 37,
        "driven_distance": 280.605804349,
        "avg_speed": 7.58394065808,
        "all_stop_times": 1,
        "all_waiting_time": 11,
        "all_waiting_time/driven_time": 0.297297297297,
        "in_road_time": 2,
        "in_road_distance": 33.34,
        "in_road_stop_times": 0,
        "in_road_waiting_time": 0
    },
    {
        "id": 13,
        "latitude": 22.5472189522,
        "longitude": 114.084115413,
        "speed": 0,
        "driven_time": 36,
        "driven_distance": 426.957282459,
        "avg_speed": 11.8599245127,
        "all_stop_times": 1,
        "all_waiting_time": 5,
        "all_waiting_time/driven_time": 0.138888888889,
        "in_road_time": 36,
        "in_road_distance": 426.957282459,
        "in_road_stop_times": 1,
        "in_road_waiting_time": 5
    },
    {
        "id": 14,
        "latitude": 22.5490515735,
        "longitude": 114.080410862,
        "speed": 0,
        "driven_time": 36,
        "driven_distance": 116.320740335,
        "avg_speed": 3.23113167596,
        "all_stop_times": 1,
        "all_waiting_time": 24,
        "all_waiting_time/driven_time": 0.666666666667,
        "in_road_time": 36,
        "in_road_distance": 116.320740335,
        "in_road_stop_times": 1,
        "in_road_waiting_time": 24
    },
    {
        "id": 15,
        "latitude": 22.5480907198,
        "longitude": 114.078454193,
        "speed": 16.67,
        "driven_time": 36,
        "driven_distance": 243.608341181,
        "avg_speed": 6.76689836615,
        "all_stop_times": 2,
        "all_waiting_time": 12,
        "all_waiting_time/driven_time": 0.333333333333,
        "in_road_time": 13,
        "in_road_distance": 114.01,
        "in_road_stop_times": 1,
        "in_road_waiting_time": 2
    },
    {
        "id": 16,
        "latitude": 22.5432794441,
        "longitude": 114.086918913,
        "speed": 16.67,
        "driven_time": 35,
        "driven_distance": 522.09,
        "avg_speed": 14.9168571429,
        "all_stop_times": 0,
        "all_waiting_time": 0,
        "all_waiting_time/driven_time": 0,
        "in_road_time": 35,
        "in_road_distance": 522.09,
        "in_road_stop_times": 0,
        "in_road_waiting_time": 0
    },
    {
        "id": 17,
        "latitude": 22.5504139479,
        "longitude": 114.07840999,
        "speed": 0,
        "driven_time": 35,
        "driven_distance": 221.389797957,
        "avg_speed": 6.32542279879,
        "all_stop_times": 1,
        "all_waiting_time": 14,
        "all_waiting_time/driven_time": 0.4,
        "in_road_time": 24,
        "in_road_distance": 109.544469277,
        "in_road_stop_times": 1,
        "in_road_waiting_time": 14
    },
    {
        "id": 18,
        "latitude": 22.5504144209,
        "longitude": 114.078450586,
        "speed": 0,
        "driven_time": 35,
        "driven_distance": 114.544469277,
        "avg_speed": 3.2726991222,
        "all_stop_times": 1,
        "all_waiting_time": 23,
        "all_waiting_time/driven_time": 0.657142857143,
        "in_road_time": 35,
        "in_road_distance": 114.544469277,
        "in_road_stop_times": 1,
        "in_road_waiting_time": 23
    },
    {
        "id": 19,
        "latitude": 22.5492750905,
        "longitude": 114.082640911,
        "speed": 16.67,
        "driven_time": 35,
        "driven_distance": 389.263679661,
        "avg_speed": 11.1218194189,
        "all_stop_times": 1,
        "all_waiting_time": 3,
        "all_waiting_time/driven_time": 0.0857142857143,
        "in_road_time": 13,
        "in_road_distance": 155.35,
        "in_road_stop_times": 0,
        "in_road_waiting_time": 0
    },
    {
        "id": 20,
        "latitude": 22.5492345423,
        "longitude": 114.083947453,
        "speed": 0,
        "driven_time": 35,
        "driven_distance": 238.640127098,
        "avg_speed": 6.81828934566,
        "all_stop_times": 1,
        "all_waiting_time": 15,
        "all_waiting_time/driven_time": 0.428571428571,
        "in_road_time": 35,
        "in_road_distance": 238.640127098,
        "in_road_stop_times": 1,
        "in_road_waiting_time": 15
    },
    {
        "id": 21,
        "latitude": 22.545426958,
        "longitude": 114.080342573,
        "speed": 0,
        "driven_time": 34,
        "driven_distance": 131.749912943,
        "avg_speed": 3.87499743949,
        "all_stop_times": 1,
        "all_waiting_time": 21,
        "all_waiting_time/driven_time": 0.617647058824,
        "in_road_time": 34,
        "in_road_distance": 131.749912943,
        "in_road_stop_times": 1,
        "in_road_waiting_time": 21
    },
    {
        "id": 22,
        "latitude": 22.5470448614,
        "longitude": 114.082822766,
        "speed": 0,
        "driven_time": 34,
        "driven_distance": 152.685354237,
        "avg_speed": 4.49074571284,
        "all_stop_times": 1,
        "all_waiting_time": 19,
        "all_waiting_time/driven_time": 0.558823529412,
        "in_road_time": 34,
        "in_road_distance": 152.685354237,
        "in_road_stop_times": 1,
        "in_road_waiting_time": 19
    },
    {
        "id": 23,
        "latitude": 22.5491567618,
        "longitude": 114.078607164,
        "speed": 0,
        "driven_time": 34,
        "driven_distance": 283.880725047,
        "avg_speed": 8.34943308962,
        "all_stop_times": 1,
        "all_waiting_time": 12,
        "all_waiting_time/driven_time": 0.352941176471,
        "in_road_time": 25.3242824254,
        "in_road_distance": 220.494375904,
        "in_road_stop_times": 1,
        "in_road_waiting_time": 12
    },
    {
        "id": 24,
        "latitude": 22.5453463235,
        "longitude": 114.087192636,
        "speed": 16.67,
        "driven_time": 34,
        "driven_distance": 501.460466421,
        "avg_speed": 14.7488372477,
        "all_stop_times": 0,
        "all_waiting_time": 0,
        "all_waiting_time/driven_time": 0,
        "in_road_time": 21,
        "in_road_distance": 350.07,
        "in_road_stop_times": 0,
        "in_road_waiting_time": 0
    },
    {
        "id": 25,
        "latitude": 22.5490986107,
        "longitude": 114.078471016,
        "speed": 0,
        "driven_time": 34,
        "driven_distance": 118.115949227,
        "avg_speed": 3.47399850667,
        "all_stop_times": 1,
        "all_waiting_time": 22,
        "all_waiting_time/driven_time": 0.647058823529,
        "in_road_time": 34,
        "in_road_distance": 118.115949227,
        "in_road_stop_times": 1,
        "in_road_waiting_time": 22
    },
    {
        "id": 26,
        "latitude": 22.5485948615,
        "longitude": 114.087837873,
        "speed": 16.67,
        "driven_time": 34,
        "driven_distance": 492.526517126,
        "avg_speed": 14.4860740331,
        "all_stop_times": 0,
        "all_waiting_time": 0,
        "all_waiting_time/driven_time": 0,
        "in_road_time": 4,
        "in_road_distance": 66.68,
        "in_road_stop_times": 0,
        "in_road_waiting_time": 0
    },
    {
        "id": 27,
        "latitude": 22.550604443,
        "longitude": 114.077592982,
        "speed": 16.67,
        "driven_time": 34,
        "driven_distance": 217.40839259,
        "avg_speed": 6.39436448795,
        "all_stop_times": 2,
        "all_waiting_time": 10,
        "all_waiting_time/driven_time": 0.294117647059,
        "in_road_time": 11,
        "in_road_distance": 105.34,
        "in_road_stop_times": 1,
        "in_road_waiting_time": 1
    },
    {
        "id": 28,
        "latitude": 22.5502464477,
        "longitude": 114.078409441,
        "speed": 6.67,
        "driven_time": 34,
        "driven_distance": 338.17865448,
        "avg_speed": 9.94643101412,
        "all_stop_times": 1,
        "all_waiting_time": 4,
        "all_waiting_time/driven_time": 0.117647058824,
        "in_road_time": 2,
        "in_road_distance": 18.34,
        "in_road_stop_times": 0,
        "in_road_waiting_time": 0
    },
    {
        "id": 29,
        "latitude": 22.5505328608,
        "longitude": 114.080342491,
        "speed": 0,
        "driven_time": 34,
        "driven_distance": 309.385431084,
        "avg_speed": 9.09957150248,
        "all_stop_times": 2,
        "all_waiting_time": 6,
        "all_waiting_time/driven_time": 0.176470588235,
        "in_road_time": 13,
        "in_road_distance": 112.108945407,
        "in_road_stop_times": 1,
        "in_road_waiting_time": 1
    },
    {
        "id": 30,
        "latitude": 22.54380882,
        "longitude": 114.08783952,
        "speed": 16.67,
        "driven_time": 33,
        "driven_distance": 460.478595735,
        "avg_speed": 13.9538968405,
        "all_stop_times": 0,
        "all_waiting_time": 0,
        "all_waiting_time/driven_time": 0,
        "in_road_time": 10,
        "in_road_distance": 166.7,
        "in_road_stop_times": 0,
        "in_road_waiting_time": 0
    },
    {
        "id": 31,
        "latitude": 22.5477073827,
        "longitude": 114.078471174,
        "speed": 16.67,
        "driven_time": 33,
        "driven_distance": 367.40166086,
        "avg_speed": 11.1333836624,
        "all_stop_times": 1,
        "all_waiting_time": 2,
        "all_waiting_time/driven_time": 0.0606060606061,
        "in_road_time": 13,
        "in_road_distance": 155.35,
        "in_road_stop_times": 0,
        "in_road_waiting_time": 0
    },
    {
        "id": 32,
        "latitude": 22.546925329,
        "longitude": 114.076239479,
        "speed": 0,
        "driven_time": 31,
        "driven_distance": 163.242303678,
        "avg_speed": 5.26588076381,
        "all_stop_times": 2,
        "all_waiting_time": 14,
        "all_waiting_time/driven_time": 0.451612903226,
        "in_road_time": 31,
        "in_road_distance": 163.242303678,
        "in_road_stop_times": 2,
        "in_road_waiting_time": 14
    },
    {
        "id": 33,
        "latitude": 22.5455089073,
        "longitude": 114.082620399,
        "speed": 0,
        "driven_time": 31,
        "driven_distance": 254.449459781,
        "avg_speed": 8.20804708972,
        "all_stop_times": 1,
        "all_waiting_time": 10,
        "all_waiting_time/driven_time": 0.322580645161,
        "in_road_time": 31,
        "in_road_distance": 254.449459781,
        "in_road_stop_times": 1,
        "in_road_waiting_time": 10
    },
    {
        "id": 34,
        "latitude": 22.5492883853,
        "longitude": 114.083896928,
        "speed": 11.67,
        "driven_time": 31,
        "driven_distance": 437.516517126,
        "avg_speed": 14.1134360363,
        "all_stop_times": 0,
        "all_waiting_time": 0,
        "all_waiting_time/driven_time": 0,
        "in_road_time": 1,
        "in_road_distance": 11.67,
        "in_road_stop_times": 0,
        "in_road_waiting_time": 0
    },
    {
        "id": 35,
        "latitude": 22.5494722571,
        "longitude": 114.079256541,
        "speed": 16.67,
        "driven_time": 30,
        "driven_distance": 217.464837503,
        "avg_speed": 7.24882791675,
        "all_stop_times": 2,
        "all_waiting_time": 6,
        "all_waiting_time/driven_time": 0.2,
        "in_road_time": 11,
        "in_road_distance": 105.34,
        "in_road_stop_times": 1,
        "in_road_waiting_time": 1
    },
    {
        "id": 36,
        "latitude": 22.5482653872,
        "longitude": 114.091041843,
        "speed": 16.67,
        "driven_time": 30,
        "driven_distance": 326.709620303,
        "avg_speed": 10.8903206768,
        "all_stop_times": 0,
        "all_waiting_time": 0,
        "all_waiting_time/driven_time": 0,
        "in_road_time": 11,
        "in_road_distance": 94.37,
        "in_road_stop_times": 0,
        "in_road_waiting_time": 0
    },
    {
        "id": 37,
        "latitude": 22.5455002133,
        "longitude": 114.08802549,
        "speed": 0,
        "driven_time": 29,
        "driven_distance": 350.887970411,
        "avg_speed": 12.0995851866,
        "all_stop_times": 1,
        "all_waiting_time": 3,
        "all_waiting_time/driven_time": 0.103448275862,
        "in_road_time": 29,
        "in_road_distance": 350.887970411,
        "in_road_stop_times": 1,
        "in_road_waiting_time": 3
    },
    {
        "id": 38,
        "latitude": 22.5471807007,
        "longitude": 114.076870423,
        "speed": 16.67,
        "driven_time": 29,
        "driven_distance": 420.534375904,
        "avg_speed": 14.501185376,
        "all_stop_times": 0,
        "all_waiting_time": 0,
        "all_waiting_time/driven_time": 0,
        "in_road_time": 12,
        "in_road_distance": 200.04,
        "in_road_stop_times": 0,
        "in_road_waiting_time": 0
    },
    {
        "id": 39,
        "latitude": 22.5514488435,
        "longitude": 114.078017199,
        "speed": 14,
        "driven_time": 29,
        "driven_distance": 188.971077859,
        "avg_speed": 6.51624406409,
        "all_stop_times": 3,
        "all_waiting_time": 5,
        "all_waiting_time/driven_time": 0.172413793103,
        "in_road_time": 11,
        "in_road_distance": 62,
        "in_road_stop_times": 2,
        "in_road_waiting_time": 2
    },
    {
        "id": 40,
        "latitude": 22.5472240002,
        "longitude": 114.084311726,
        "speed": 15.8068206147,
        "driven_time": 28,
        "driven_distance": 404.536820615,
        "avg_speed": 14.4477435934,
        "all_stop_times": 0,
        "all_waiting_time": 0,
        "all_waiting_time/driven_time": 0,
        "in_road_time": 28,
        "in_road_distance": 404.536820615,
        "in_road_stop_times": 0,
        "in_road_waiting_time": 0
    },
    {
        "id": 41,
        "latitude": 22.5490512236,
        "longitude": 114.080370199,
        "speed": 0,
        "driven_time": 28,
        "driven_distance": 111.320740335,
        "avg_speed": 3.97574072623,
        "all_stop_times": 1,
        "all_waiting_time": 15,
        "all_waiting_time/driven_time": 0.535714285714,
        "in_road_time": 28,
        "in_road_distance": 111.320740335,
        "in_road_stop_times": 1,
        "in_road_waiting_time": 15
    },
    {
        "id": 42,
        "latitude": 22.5490498728,
        "longitude": 114.077282426,
        "speed": 11.67,
        "driven_time": 28,
        "driven_distance": 264.384290408,
        "avg_speed": 9.44229608601,
        "all_stop_times": 1,
        "all_waiting_time": 2,
        "all_waiting_time/driven_time": 0.0714285714286,
        "in_road_time": 1,
        "in_road_distance": 11.67,
        "in_road_stop_times": 0,
        "in_road_waiting_time": 0
    },
    {
        "id": 43,
        "latitude": 22.5431352955,
        "longitude": 114.085339594,
        "speed": 16.67,
        "driven_time": 27,
        "driven_distance": 342.72,
        "avg_speed": 12.6933333333,
        "all_stop_times": 0,
        "all_waiting_time": 0,
        "all_waiting_time/driven_time": 0,
        "in_road_time": 27,
        "in_road_distance": 342.72,
        "in_road_stop_times": 0,
        "in_road_waiting_time": 0
    },
    {
        "id": 44,
        "latitude": 22.5490111119,
        "longitude": 114.077258325,
        "speed": 16.67,
        "driven_time": 27,
        "driven_distance": 264.40502282,
        "avg_speed": 9.79277862296,
        "all_stop_times": 1,
        "all_waiting_time": 2,
        "all_waiting_time/driven_time": 0.0740740740741,
        "in_road_time": 1,
        "in_road_distance": 16.67,
        "in_road_stop_times": 0,
        "in_road_waiting_time": 0
    },
    {
        "id": 45,
        "latitude": 22.5503644243,
        "longitude": 114.078451168,
        "speed": 0,
        "driven_time": 27,
        "driven_distance": 114.544469277,
        "avg_speed": 4.242387751,
        "all_stop_times": 2,
        "all_waiting_time": 14,
        "all_waiting_time/driven_time": 0.518518518519,
        "in_road_time": 27,
        "in_road_distance": 114.544469277,
        "in_road_stop_times": 2,
        "in_road_waiting_time": 14
    },
    {
        "id": 46,
        "latitude": 22.5492255855,
        "longitude": 114.082687946,
        "speed": 16.67,
        "driven_time": 27,
        "driven_distance": 383.943679661,
        "avg_speed": 14.2201362838,
        "all_stop_times": 0,
        "all_waiting_time": 0,
        "all_waiting_time/driven_time": 0,
        "in_road_time": 9,
        "in_road_distance": 150.03,
        "in_road_stop_times": 0,
        "in_road_waiting_time": 0
    },
    {
        "id": 47,
        "latitude": 22.5492372349,
        "longitude": 114.08399738,
        "speed": 0,
        "driven_time": 27,
        "driven_distance": 238.640127098,
        "avg_speed": 8.83852322585,
        "all_stop_times": 1,
        "all_waiting_time": 7,
        "all_waiting_time/driven_time": 0.259259259259,
        "in_road_time": 27,
        "in_road_distance": 238.640127098,
        "in_road_stop_times": 1,
        "in_road_waiting_time": 7
    },
    {
        "id": 48,
        "latitude": 22.5454764603,
        "longitude": 114.080335535,
        "speed": 0,
        "driven_time": 26,
        "driven_distance": 131.749912943,
        "avg_speed": 5.06730434395,
        "all_stop_times": 1,
        "all_waiting_time": 13,
        "all_waiting_time/driven_time": 0.5,
        "in_road_time": 26,
        "in_road_distance": 131.749912943,
        "in_road_stop_times": 1,
        "in_road_waiting_time": 13
    },
    {
        "id": 49,
        "latitude": 22.5469995035,
        "longitude": 114.08282078,
        "speed": 0,
        "driven_time": 26,
        "driven_distance": 147.685354237,
        "avg_speed": 5.68020593218,
        "all_stop_times": 2,
        "all_waiting_time": 10,
        "all_waiting_time/driven_time": 0.384615384615,
        "in_road_time": 26,
        "in_road_distance": 147.685354237,
        "in_road_stop_times": 2,
        "in_road_waiting_time": 10
    },
    {
        "id": 50,
        "latitude": 22.5471603484,
        "longitude": 114.078699297,
        "speed": 0,
        "driven_time": 26,
        "driven_distance": 63.386349143,
        "avg_speed": 2.4379365055,
        "all_stop_times": 1,
        "all_waiting_time": 18,
        "all_waiting_time/driven_time": 0.692307692308,
        "in_road_time": 25.4616468214,
        "in_road_distance": 63.386349143,
        "in_road_stop_times": 1,
        "in_road_waiting_time": 18
    },
    {
        "id": 51,
        "latitude": 22.5435722213,
        "longitude": 114.0839796,
        "speed": 16.67,
        "driven_time": 26,
        "driven_distance": 368.017444035,
        "avg_speed": 14.1545170783,
        "all_stop_times": 0,
        "all_waiting_time": 0,
        "all_waiting_time/driven_time": 0,
        "in_road_time": 13,
        "in_road_distance": 216.626977614,
        "in_road_stop_times": 0,
        "in_road_waiting_time": 0
    },
    {
        "id": 52,
        "latitude": 22.5507486371,
        "longitude": 114.080335767,
        "speed": 15.67,
        "driven_time": 26,
        "driven_distance": 284.976485677,
        "avg_speed": 10.9606340645,
        "all_stop_times": 0,
        "all_waiting_time": 0,
        "all_waiting_time/driven_time": 0,
        "in_road_time": 10,
        "in_road_distance": 87.7,
        "in_road_stop_times": 0,
        "in_road_waiting_time": 0
    },
    {
        "id": 53,
        "latitude": 22.545646625,
        "longitude": 114.087829112,
        "speed": 16.67,
        "driven_time": 25,
        "driven_distance": 272.193633818,
        "avg_speed": 10.8877453527,
        "all_stop_times": 0,
        "all_waiting_time": 0,
        "all_waiting_time/driven_time": 0,
        "in_road_time": 13,
        "in_road_distance": 165.039585157,
        "in_road_stop_times": 0,
        "in_road_waiting_time": 0
    },
    {
        "id": 54,
        "latitude": 22.5504172271,
        "longitude": 114.078552132,
        "speed": 0,
        "driven_time": 25,
        "driven_distance": 252.714290408,
        "avg_speed": 10.1085716163,
        "all_stop_times": 1,
        "all_waiting_time": 2,
        "all_waiting_time/driven_time": 0.08,
        "in_road_time": 11,
        "in_road_distance": 129.598341181,
        "in_road_stop_times": 1,
        "in_road_waiting_time": 2
    },
    {
        "id": 55,
        "latitude": 22.5491934283,
        "longitude": 114.079463568,
        "speed": 0,
        "driven_time": 25,
        "driven_distance": 116.320740335,
        "avg_speed": 4.65282961338,
        "all_stop_times": 1,
        "all_waiting_time": 13,
        "all_waiting_time/driven_time": 0.52,
        "in_road_time": 25,
        "in_road_distance": 116.320740335,
        "in_road_stop_times": 1,
        "in_road_waiting_time": 13
    },
    {
        "id": 56,
        "latitude": 22.5491450704,
        "longitude": 114.086939436,
        "speed": 16.67,
        "driven_time": 25,
        "driven_distance": 324.05,
        "avg_speed": 12.962,
        "all_stop_times": 1,
        "all_waiting_time": 1,
        "all_waiting_time/driven_time": 0.04,
        "in_road_time": 25,
        "in_road_distance": 324.05,
        "in_road_stop_times": 1,
        "in_road_waiting_time": 1
    },
    {
        "id": 57,
        "latitude": 22.5506090156,
        "longitude": 114.077985463,
        "speed": 14,
        "driven_time": 25,
        "driven_distance": 169.06839259,
        "avg_speed": 6.76273570361,
        "all_stop_times": 2,
        "all_waiting_time": 2,
        "all_waiting_time/driven_time": 0.08,
        "in_road_time": 9,
        "in_road_distance": 57,
        "in_road_stop_times": 1,
        "in_road_waiting_time": 1
    },
    {
        "id": 58,
        "latitude": 22.5516155607,
        "longitude": 114.079395433,
        "speed": 0,
        "driven_time": 25,
        "driven_distance": 118.325118043,
        "avg_speed": 4.73300472171,
        "all_stop_times": 1,
        "all_waiting_time": 13,
        "all_waiting_time/driven_time": 0.52,
        "in_road_time": 25,
        "in_road_distance": 118.325118043,
        "in_road_stop_times": 1,
        "in_road_waiting_time": 13
    },
    {
        "id": 59,
        "latitude": 22.5469698202,
        "longitude": 114.076188391,
        "speed": 0,
        "driven_time": 23,
        "driven_distance": 168.242303678,
        "avg_speed": 7.31488276862,
        "all_stop_times": 1,
        "all_waiting_time": 8,
        "all_waiting_time/driven_time": 0.347826086957,
        "in_road_time": 23,
        "in_road_distance": 168.242303678,
        "in_road_stop_times": 1,
        "in_road_waiting_time": 8
    },
    {
        "id": 60,
        "latitude": 22.5455603358,
        "longitude": 114.082661722,
        "speed": 0,
        "driven_time": 23,
        "driven_distance": 259.449459781,
        "avg_speed": 11.2804112948,
        "all_stop_times": 1,
        "all_waiting_time": 2,
        "all_waiting_time/driven_time": 0.0869565217391,
        "in_road_time": 23,
        "in_road_distance": 259.449459781,
        "in_road_stop_times": 1,
        "in_road_waiting_time": 2
    },
    {
        "id": 61,
        "latitude": 22.5493582544,
        "longitude": 114.085006024,
        "speed": 16.67,
        "driven_time": 23,
        "driven_distance": 322.05,
        "avg_speed": 14.002173913,
        "all_stop_times": 0,
        "all_waiting_time": 0,
        "all_waiting_time/driven_time": 0,
        "in_road_time": 23,
        "in_road_distance": 322.05,
        "in_road_stop_times": 0,
        "in_road_waiting_time": 0
    },
    {
        "id": 62,
        "latitude": 22.5505655038,
        "longitude": 114.078548979,
        "speed": 0,
        "driven_time": 22,
        "driven_distance": 210.431561425,
        "avg_speed": 9.56507097387,
        "all_stop_times": 1,
        "all_waiting_time": 3,
        "all_waiting_time/driven_time": 0.136363636364,
        "in_road_time": 11,
        "in_road_distance": 98.3067239226,
        "in_road_stop_times": 1,
        "in_road_waiting_time": 3
    },
    {
        "id": 63,
        "latitude": 22.549358252,
        "longitude": 114.090513973,
        "speed": 16.67,
        "driven_time": 22,
        "driven_distance": 299.019620303,
        "avg_speed": 13.5918009229,
        "all_stop_times": 0,
        "all_waiting_time": 0,
        "all_waiting_time/driven_time": 0,
        "in_road_time": 4,
        "in_road_distance": 66.68,
        "in_road_stop_times": 0,
        "in_road_waiting_time": 0
    },
    {
        "id": 64,
        "latitude": 22.54550436,
        "longitude": 114.088567151,
        "speed": 16.67,
        "driven_time": 21,
        "driven_distance": 288.71,
        "avg_speed": 13.7480952381,
        "all_stop_times": 0,
        "all_waiting_time": 0,
        "all_waiting_time/driven_time": 0,
        "in_road_time": 21,
        "in_road_distance": 288.71,
        "in_road_stop_times": 0,
        "in_road_waiting_time": 0
    },
    {
        "id": 65,
        "latitude": 22.5471996709,
        "longitude": 114.078021832,
        "speed": 16.67,
        "driven_time": 21,
        "driven_distance": 287.174375904,
        "avg_speed": 13.6749702811,
        "all_stop_times": 0,
        "all_waiting_time": 0,
        "all_waiting_time/driven_time": 0,
        "in_road_time": 4,
        "in_road_distance": 66.68,
        "in_road_stop_times": 0,
        "in_road_waiting_time": 0
    },
    {
        "id": 66,
        "latitude": 22.5514541646,
        "longitude": 114.078449969,
        "speed": 16.67,
        "driven_time": 21,
        "driven_distance": 242.001077859,
        "avg_speed": 11.5238608504,
        "all_stop_times": 0,
        "all_waiting_time": 0,
        "all_waiting_time/driven_time": 0,
        "in_road_time": 9,
        "in_road_distance": 115.03,
        "in_road_stop_times": 0,
        "in_road_waiting_time": 0
    },
    {
        "id": 67,
        "latitude": 22.5472538319,
        "longitude": 114.085471867,
        "speed": 16.67,
        "driven_time": 20,
        "driven_distance": 272.04,
        "avg_speed": 13.602,
        "all_stop_times": 0,
        "all_waiting_time": 0,
        "all_waiting_time/driven_time": 0,
        "in_road_time": 20,
        "in_road_distance": 272.04,
        "in_road_stop_times": 0,
        "in_road_waiting_time": 0
    },
    {
        "id": 68,
        "latitude": 22.5490508738,
        "longitude": 114.080329535,
        "speed": 0,
        "driven_time": 20,
        "driven_distance": 106.320740335,
        "avg_speed": 5.31603701673,
        "all_stop_times": 1,
        "all_waiting_time": 8,
        "all_waiting_time/driven_time": 0.4,
        "in_road_time": 20,
        "in_road_distance": 106.320740335,
        "in_road_stop_times": 1,
        "in_road_waiting_time": 8
    },
    {
        "id": 69,
        "latitude": 22.5492889446,
        "longitude": 114.077577618,
        "speed": 16.67,
        "driven_time": 20,
        "driven_distance": 241.958341181,
        "avg_speed": 12.0979170591,
        "all_stop_times": 0,
        "all_waiting_time": 0,
        "all_waiting_time/driven_time": 0,
        "in_road_time": 8,
        "in_road_distance": 112.36,
        "in_road_stop_times": 0,
        "in_road_waiting_time": 0
    },
    {
        "id": 70,
        "latitude": 22.5430958869,
        "longitude": 114.084677902,
        "speed": 16.67,
        "driven_time": 19,
        "driven_distance": 267.71,
        "avg_speed": 14.09,
        "all_stop_times": 0,
        "all_waiting_time": 0,
        "all_waiting_time/driven_time": 0,
        "in_road_time": 19,
        "in_road_distance": 267.71,
        "in_road_stop_times": 0,
        "in_road_waiting_time": 0
    },
    {
        "id": 71,
        "latitude": 22.5493932738,
        "longitude": 114.077353969,
        "speed": 16.67,
        "driven_time": 19,
        "driven_distance": 224.20532868,
        "avg_speed": 11.8002804569,
        "all_stop_times": 0,
        "all_waiting_time": 0,
        "all_waiting_time/driven_time": 0,
        "in_road_time": 8,
        "in_road_distance": 112.36,
        "in_road_stop_times": 0,
        "in_road_waiting_time": 0
    },
    {
        "id": 72,
        "latitude": 22.5503639513,
        "longitude": 114.078410572,
        "speed": 0,
        "driven_time": 19,
        "driven_distance": 109.544469277,
        "avg_speed": 5.765498383,
        "all_stop_times": 1,
        "all_waiting_time": 6,
        "all_waiting_time/driven_time": 0.315789473684,
        "in_road_time": 19,
        "in_road_distance": 109.544469277,
        "in_road_stop_times": 1,
        "in_road_waiting_time": 6
    },
    {
        "id": 73,
        "latitude": 22.5492379255,
        "longitude": 114.083853748,
        "speed": 16.67,
        "driven_time": 19,
        "driven_distance": 250.583679661,
        "avg_speed": 13.188614719,
        "all_stop_times": 0,
        "all_waiting_time": 0,
        "all_waiting_time/driven_time": 0,
        "in_road_time": 1,
        "in_road_distance": 16.67,
        "in_road_stop_times": 0,
        "in_road_waiting_time": 0
    },
    {
        "id": 74,
        "latitude": 22.5493067219,
        "longitude": 114.083993633,
        "speed": 7.47006354896,
        "driven_time": 19,
        "driven_distance": 231.170063549,
        "avg_speed": 12.1668454499,
        "all_stop_times": 0,
        "all_waiting_time": 0,
        "all_waiting_time/driven_time": 0,
        "in_road_time": 19,
        "in_road_distance": 231.170063549,
        "in_road_stop_times": 0,
        "in_road_waiting_time": 0
    },
    {
        "id": 75,
        "latitude": 22.5454706567,
        "longitude": 114.080294712,
        "speed": 0,
        "driven_time": 18,
        "driven_distance": 126.749912943,
        "avg_speed": 7.04166183015,
        "all_stop_times": 1,
        "all_waiting_time": 4,
        "all_waiting_time/driven_time": 0.222222222222,
        "in_road_time": 18,
        "in_road_distance": 126.749912943,
        "in_road_stop_times": 1,
        "in_road_waiting_time": 4
    },
    {
        "id": 76,
        "latitude": 22.5469541457,
        "longitude": 114.082818795,
        "speed": 0,
        "driven_time": 18,
        "driven_distance": 142.685354237,
        "avg_speed": 7.92696412426,
        "all_stop_times": 1,
        "all_waiting_time": 3,
        "all_waiting_time/driven_time": 0.166666666667,
        "in_road_time": 18,
        "in_road_distance": 142.685354237,
        "in_road_stop_times": 1,
        "in_road_waiting_time": 3
    },
    {
        "id": 77,
        "latitude": 22.5471606086,
        "longitude": 114.078736371,
        "speed": 0,
        "driven_time": 18,
        "driven_distance": 58.386349143,
        "avg_speed": 3.2436860635,
        "all_stop_times": 1,
        "all_waiting_time": 9,
        "all_waiting_time/driven_time": 0.5,
        "in_road_time": 18,
        "in_road_distance": 58.386349143,
        "in_road_stop_times": 1,
        "in_road_waiting_time": 9
    },
    {
        "id": 78,
        "latitude": 22.5448141238,
        "longitude": 114.083954643,
        "speed": 16.67,
        "driven_time": 18,
        "driven_distance": 234.740466421,
        "avg_speed": 13.0411370234,
        "all_stop_times": 0,
        "all_waiting_time": 0,
        "all_waiting_time/driven_time": 0,
        "in_road_time": 5,
        "in_road_distance": 83.35,
        "in_road_stop_times": 0,
        "in_road_waiting_time": 0
    },
    {
        "id": 79,
        "latitude": 22.5512291821,
        "longitude": 114.080320791,
        "speed": 16.67,
        "driven_time": 18,
        "driven_distance": 230.616485677,
        "avg_speed": 12.8120269821,
        "all_stop_times": 0,
        "all_waiting_time": 0,
        "all_waiting_time/driven_time": 0,
        "in_road_time": 2,
        "in_road_distance": 33.34,
        "in_road_stop_times": 0,
        "in_road_waiting_time": 0
    },
    {
        "id": 80,
        "latitude": 22.5462447928,
        "longitude": 114.087820454,
        "speed": 16.67,
        "driven_time": 17,
        "driven_distance": 207.174048661,
        "avg_speed": 12.1867087448,
        "all_stop_times": 0,
        "all_waiting_time": 0,
        "all_waiting_time/driven_time": 0,
        "in_road_time": 6,
        "in_road_distance": 100.02,
        "in_road_stop_times": 0,
        "in_road_waiting_time": 0
    },
    {
        "id": 81,
        "latitude": 22.5491937782,
        "longitude": 114.079504232,
        "speed": 0,
        "driven_time": 17,
        "driven_distance": 111.320740335,
        "avg_speed": 6.54827884321,
        "all_stop_times": 1,
        "all_waiting_time": 4,
        "all_waiting_time/driven_time": 0.235294117647,
        "in_road_time": 17,
        "in_road_distance": 111.320740335,
        "in_road_stop_times": 1,
        "in_road_waiting_time": 4
    },
    {
        "id": 82,
        "latitude": 22.549853773,
        "longitude": 114.078576718,
        "speed": 16.67,
        "driven_time": 16,
        "driven_distance": 189.795949227,
        "avg_speed": 11.8622468267,
        "all_stop_times": 0,
        "all_waiting_time": 0,
        "all_waiting_time/driven_time": 0,
        "in_road_time": 4,
        "in_road_distance": 66.68,
        "in_road_stop_times": 0,
        "in_road_waiting_time": 0
    },
    {
        "id": 83,
        "latitude": 22.5491288182,
        "longitude": 114.086086992,
        "speed": 16.67,
        "driven_time": 16,
        "driven_distance": 226.7,
        "avg_speed": 14.16875,
        "all_stop_times": 0,
        "all_waiting_time": 0,
        "all_waiting_time/driven_time": 0,
        "in_road_time": 16,
        "in_road_distance": 226.7,
        "in_road_stop_times": 0,
        "in_road_waiting_time": 0
    },
    {
        "id": 84,
        "latitude": 22.5506116311,
        "longitude": 114.078209958,
        "speed": 5.67,
        "driven_time": 16,
        "driven_distance": 141.41839259,
        "avg_speed": 8.83864953689,
        "all_stop_times": 0,
        "all_waiting_time": 0,
        "all_waiting_time/driven_time": 0,
        "in_road_time": 5,
        "in_road_distance": 29.35,
        "in_road_stop_times": 0,
        "in_road_waiting_time": 0
    },
    {
        "id": 85,
        "latitude": 22.5516160201,
        "longitude": 114.079436168,
        "speed": 0,
        "driven_time": 16,
        "driven_distance": 113.325118043,
        "avg_speed": 7.08281987767,
        "all_stop_times": 2,
        "all_waiting_time": 2,
        "all_waiting_time/driven_time": 0.125,
        "in_road_time": 16,
        "in_road_distance": 113.325118043,
        "in_road_stop_times": 2,
        "in_road_waiting_time": 2
    },
    {
        "id": 86,
        "latitude": 22.5468825182,
        "longitude": 114.076190497,
        "speed": 1.67,
        "driven_time": 15,
        "driven_distance": 158.69,
        "avg_speed": 10.5793333333,
        "all_stop_times": 0,
        "all_waiting_time": 0,
        "all_waiting_time/driven_time": 0,
        "in_road_time": 15,
        "in_road_distance": 158.69,
        "in_road_stop_times": 0,
        "in_road_waiting_time": 0
    },
    {
        "id": 87,
        "latitude": 22.5455397136,
        "longitude": 114.082052974,
        "speed": 16.67,
        "driven_time": 15,
        "driven_distance": 188.69,
        "avg_speed": 12.5793333333,
        "all_stop_times": 0,
        "all_waiting_time": 0,
        "all_waiting_time/driven_time": 0,
        "in_road_time": 15,
        "in_road_distance": 188.69,
        "in_road_stop_times": 0,
        "in_road_waiting_time": 0
    },
    {
        "id": 88,
        "latitude": 22.5493805184,
        "longitude": 114.086173789,
        "speed": 16.67,
        "driven_time": 15,
        "driven_distance": 188.69,
        "avg_speed": 12.5793333333,
        "all_stop_times": 0,
        "all_waiting_time": 0,
        "all_waiting_time/driven_time": 0,
        "in_road_time": 15,
        "in_road_distance": 188.69,
        "in_road_stop_times": 0,
        "in_road_waiting_time": 0
    },
    {
        "id": 89,
        "latitude": 22.5505187483,
        "longitude": 114.07923235,
        "speed": 16.67,
        "driven_time": 14,
        "driven_distance": 112.124837503,
        "avg_speed": 8.00891696447,
        "all_stop_times": 1,
        "all_waiting_time": 1,
        "all_waiting_time/driven_time": 0.0714285714286,
        "in_road_time": 13.047080834,
        "in_road_distance": 112.124837503,
        "in_road_stop_times": 1,
        "in_road_waiting_time": 1
    },
    {
        "id": 90,
        "latitude": 22.5498039179,
        "longitude": 114.091032554,
        "speed": 16.67,
        "driven_time": 14,
        "driven_distance": 172.02,
        "avg_speed": 12.2871428571,
        "all_stop_times": 0,
        "all_waiting_time": 0,
        "all_waiting_time/driven_time": 0,
        "in_road_time": 14,
        "in_road_distance": 172.02,
        "in_road_stop_times": 0,
        "in_road_waiting_time": 0
    },
    {
        "id": 91,
        "latitude": 22.5455132539,
        "longitude": 114.089728911,
        "speed": 16.67,
        "driven_time": 13,
        "driven_distance": 155.35,
        "avg_speed": 11.95,
        "all_stop_times": 0,
        "all_waiting_time": 0,
        "all_waiting_time/driven_time": 0,
        "in_road_time": 13,
        "in_road_distance": 155.35,
        "in_road_stop_times": 0,
        "in_road_waiting_time": 0
    },
    {
        "id": 92,
        "latitude": 22.5486379072,
        "longitude": 114.078429953,
        "speed": 10,
        "driven_time": 13,
        "driven_distance": 55,
        "avg_speed": 4.23076923077,
        "all_stop_times": 2,
        "all_waiting_time": 2,
        "all_waiting_time/driven_time": 0.153846153846,
        "in_road_time": 13,
        "in_road_distance": 55,
        "in_road_stop_times": 2,
        "in_road_waiting_time": 2
    },
    {
        "id": 93,
        "latitude": 22.551444295,
        "longitude": 114.077647267,
        "speed": 16.67,
        "driven_time": 13,
        "driven_distance": 143.641077859,
        "avg_speed": 11.0493136814,
        "all_stop_times": 0,
        "all_waiting_time": 0,
        "all_waiting_time/driven_time": 0,
        "in_road_time": 1,
        "in_road_distance": 16.67,
        "in_road_stop_times": 0,
        "in_road_waiting_time": 0
    },
    {
        "id": 94,
        "latitude": 22.5472838579,
        "longitude": 114.086639566,
        "speed": 16.67,
        "driven_time": 12,
        "driven_distance": 138.68,
        "avg_speed": 11.5566666667,
        "all_stop_times": 0,
        "all_waiting_time": 0,
        "all_waiting_time/driven_time": 0,
        "in_road_time": 12,
        "in_road_distance": 138.68,
        "in_road_stop_times": 0,
        "in_road_waiting_time": 0
    },
    {
        "id": 95,
        "latitude": 22.5490505239,
        "longitude": 114.080288871,
        "speed": 0,
        "driven_time": 12,
        "driven_distance": 101.320740335,
        "avg_speed": 8.44339502788,
        "all_stop_times": 1,
        "all_waiting_time": 1,
        "all_waiting_time/driven_time": 0.0833333333333,
        "in_road_time": 12,
        "in_road_distance": 101.320740335,
        "in_road_stop_times": 1,
        "in_road_waiting_time": 1
    },
    {
        "id": 96,
        "latitude": 22.5495330666,
        "longitude": 114.078440568,
        "speed": 16.5,
        "driven_time": 12,
        "driven_distance": 98,
        "avg_speed": 8.16666666667,
        "all_stop_times": 1,
        "all_waiting_time": 1,
        "all_waiting_time/driven_time": 0.0833333333333,
        "in_road_time": 12,
        "in_road_distance": 98,
        "in_road_stop_times": 1,
        "in_road_waiting_time": 1
    },
    {
        "id": 97,
        "latitude": 22.5430258225,
        "longitude": 114.083501482,
        "speed": 16.67,
        "driven_time": 11,
        "driven_distance": 134.35,
        "avg_speed": 12.2136363636,
        "all_stop_times": 0,
        "all_waiting_time": 0,
        "all_waiting_time/driven_time": 0,
        "in_road_time": 11,
        "in_road_distance": 134.35,
        "in_road_stop_times": 0,
        "in_road_waiting_time": 0
    },
    {
        "id": 98,
        "latitude": 22.5505016205,
        "longitude": 114.077319547,
        "speed": 16.67,
        "driven_time": 11,
        "driven_distance": 111.84532868,
        "avg_speed": 10.1677571528,
        "all_stop_times": 0,
        "all_waiting_time": 0,
        "all_waiting_time/driven_time": 0,
        "in_road_time": 10.3902416725,
        "in_road_distance": 111.84532868,
        "in_road_stop_times": 0,
        "in_road_waiting_time": 0
    },
    {
        "id": 99,
        "latitude": 22.5504134148,
        "longitude": 114.078364229,
        "speed": 5.63611731925,
        "driven_time": 11,
        "driven_distance": 103.908351958,
        "avg_speed": 9.44621381434,
        "all_stop_times": 0,
        "all_waiting_time": 0,
        "all_waiting_time/driven_time": 0,
        "in_road_time": 11,
        "in_road_distance": 103.908351958,
        "in_road_stop_times": 0,
        "in_road_waiting_time": 0
    },
    {
        "id": 100,
        "latitude": 22.5507134411,
        "longitude": 114.083940163,
        "speed": 15,
        "driven_time": 11,
        "driven_distance": 76,
        "avg_speed": 6.90909090909,
        "all_stop_times": 0,
        "all_waiting_time": 0,
        "all_waiting_time/driven_time": 0,
        "in_road_time": 11,
        "in_road_distance": 76,
        "in_road_stop_times": 0,
        "in_road_waiting_time": 0
    },
    {
        "id": 101,
        "latitude": 22.5503194429,
        "longitude": 114.083888945,
        "speed": 16.67,
        "driven_time": 11,
        "driven_distance": 122.01,
        "avg_speed": 11.0918181818,
        "all_stop_times": 0,
        "all_waiting_time": 0,
        "all_waiting_time/driven_time": 0,
        "in_road_time": 11,
        "in_road_distance": 122.01,
        "in_road_stop_times": 0,
        "in_road_waiting_time": 0
    },
    {
        "id": 102,
        "latitude": 22.5452964954,
        "longitude": 114.079780125,
        "speed": 14,
        "driven_time": 10,
        "driven_distance": 62,
        "avg_speed": 6.2,
        "all_stop_times": 1,
        "all_waiting_time": 1,
        "all_waiting_time/driven_time": 0.1,
        "in_road_time": 10,
        "in_road_distance": 62,
        "in_road_stop_times": 1,
        "in_road_waiting_time": 1
    },
    {
        "id": 103,
        "latitude": 22.5466153647,
        "longitude": 114.082803966,
        "speed": 16.67,
        "driven_time": 10,
        "driven_distance": 105.34,
        "avg_speed": 10.534,
        "all_stop_times": 0,
        "all_waiting_time": 0,
        "all_waiting_time/driven_time": 0,
        "in_road_time": 10,
        "in_road_distance": 105.34,
        "in_road_stop_times": 0,
        "in_road_waiting_time": 0
    },
    {
        "id": 104,
        "latitude": 22.5471103496,
        "longitude": 114.078699648,
        "speed": 0,
        "driven_time": 10,
        "driven_distance": 63.386349143,
        "avg_speed": 6.3386349143,
        "all_stop_times": 1,
        "all_waiting_time": 1,
        "all_waiting_time/driven_time": 0.1,
        "in_road_time": 10,
        "in_road_distance": 63.386349143,
        "in_road_stop_times": 1,
        "in_road_waiting_time": 1
    },
    {
        "id": 105,
        "latitude": 22.5465030027,
        "longitude": 114.083926327,
        "speed": 14,
        "driven_time": 10,
        "driven_distance": 62,
        "avg_speed": 6.2,
        "all_stop_times": 1,
        "all_waiting_time": 1,
        "all_waiting_time/driven_time": 0.1,
        "in_road_time": 10,
        "in_road_distance": 62,
        "in_road_stop_times": 1,
        "in_road_waiting_time": 1
    },
    {
        "id": 106,
        "latitude": 22.5517330792,
        "longitude": 114.081239033,
        "speed": 16.67,
        "driven_time": 10,
        "driven_distance": 105.34,
        "avg_speed": 10.534,
        "all_stop_times": 0,
        "all_waiting_time": 0,
        "all_waiting_time/driven_time": 0,
        "in_road_time": 10,
        "in_road_distance": 105.34,
        "in_road_stop_times": 0,
        "in_road_waiting_time": 0
    },
    {
        "id": 107,
        "latitude": 22.5473663174,
        "longitude": 114.088105433,
        "speed": 16.67,
        "driven_time": 9,
        "driven_distance": 88.67,
        "avg_speed": 9.85222222222,
        "all_stop_times": 0,
        "all_waiting_time": 0,
        "all_waiting_time/driven_time": 0,
        "in_road_time": 9,
        "in_road_distance": 88.67,
        "in_road_stop_times": 0,
        "in_road_waiting_time": 0
    },
    {
        "id": 108,
        "latitude": 22.5492475075,
        "longitude": 114.079937444,
        "speed": 14,
        "driven_time": 9,
        "driven_distance": 58,
        "avg_speed": 6.44444444444,
        "all_stop_times": 1,
        "all_waiting_time": 1,
        "all_waiting_time/driven_time": 0.111111111111,
        "in_road_time": 9,
        "in_road_distance": 58,
        "in_road_stop_times": 1,
        "in_road_waiting_time": 1
    },
    {
        "id": 109,
        "latitude": 22.5459452017,
        "longitude": 114.07626312,
        "speed": 14,
        "driven_time": 7,
        "driven_distance": 56,
        "avg_speed": 8,
        "all_stop_times": 0,
        "all_waiting_time": 0,
        "all_waiting_time/driven_time": 0,
        "in_road_time": 7,
        "in_road_distance": 56,
        "in_road_stop_times": 0,
        "in_road_waiting_time": 0
    },
    {
        "id": 110,
        "latitude": 22.5454510709,
        "longitude": 114.080913128,
        "speed": 14,
        "driven_time": 7,
        "driven_distance": 56,
        "avg_speed": 8,
        "all_stop_times": 0,
        "all_waiting_time": 0,
        "all_waiting_time/driven_time": 0,
        "in_road_time": 7,
        "in_road_distance": 56,
        "in_road_stop_times": 0,
        "in_road_waiting_time": 0
    },
    {
        "id": 111,
        "latitude": 22.5490644169,
        "longitude": 114.077963847,
        "speed": 14,
        "driven_time": 7,
        "driven_distance": 56,
        "avg_speed": 8,
        "all_stop_times": 0,
        "all_waiting_time": 0,
        "all_waiting_time/driven_time": 0,
        "in_road_time": 7,
        "in_road_distance": 56,
        "in_road_stop_times": 0,
        "in_road_waiting_time": 0
    },
    {
        "id": 112,
        "latitude": 22.5491503112,
        "longitude": 114.084591307,
        "speed": 14,
        "driven_time": 7,
        "driven_distance": 56,
        "avg_speed": 8,
        "all_stop_times": 0,
        "all_waiting_time": 0,
        "all_waiting_time/driven_time": 0,
        "in_road_time": 7,
        "in_road_distance": 56,
        "in_road_stop_times": 0,
        "in_road_waiting_time": 0
    },
    {
        "id": 113,
        "latitude": 22.5494026706,
        "longitude": 114.087335687,
        "speed": 14,
        "driven_time": 7,
        "driven_distance": 56,
        "avg_speed": 8,
        "all_stop_times": 0,
        "all_waiting_time": 0,
        "all_waiting_time/driven_time": 0,
        "in_road_time": 7,
        "in_road_distance": 56,
        "in_road_stop_times": 0,
        "in_road_waiting_time": 0
    },
    {
        "id": 114,
        "latitude": 22.5510123631,
        "longitude": 114.078470898,
        "speed": 14,
        "driven_time": 7,
        "driven_distance": 56,
        "avg_speed": 8,
        "all_stop_times": 0,
        "all_waiting_time": 0,
        "all_waiting_time/driven_time": 0,
        "in_road_time": 7,
        "in_road_distance": 56,
        "in_road_stop_times": 0,
        "in_road_waiting_time": 0
    },
    {
        "id": 115,
        "latitude": 22.5516734895,
        "longitude": 114.080098168,
        "speed": 10,
        "driven_time": 7,
        "driven_distance": 32,
        "avg_speed": 4.57142857143,
        "all_stop_times": 1,
        "all_waiting_time": 1,
        "all_waiting_time/driven_time": 0.142857142857,
        "in_road_time": 7,
        "in_road_distance": 32,
        "in_road_stop_times": 1,
        "in_road_waiting_time": 1
    },
    {
        "id": 116,
        "latitude": 22.551138575,
        "longitude": 114.079210762,
        "speed": 12,
        "driven_time": 6,
        "driven_distance": 42,
        "avg_speed": 7,
        "all_stop_times": 0,
        "all_waiting_time": 0,
        "all_waiting_time/driven_time": 0,
        "in_road_time": 6,
        "in_road_distance": 42,
        "in_road_stop_times": 0,
        "in_road_waiting_time": 0
    },
    {
        "id": 117,
        "latitude": 22.5508464472,
        "longitude": 114.091030941,
        "speed": 15,
        "driven_time": 6,
        "driven_distance": 60,
        "avg_speed": 10,
        "all_stop_times": 0,
        "all_waiting_time": 0,
        "all_waiting_time/driven_time": 0,
        "in_road_time": 6,
        "in_road_distance": 60,
        "in_road_stop_times": 0,
        "in_road_waiting_time": 0
    },
    {
        "id": 118,
        "latitude": 22.5455216136,
        "longitude": 114.090820892,
        "speed": 10,
        "driven_time": 5,
        "driven_distance": 30,
        "avg_speed": 6,
        "all_stop_times": 0,
        "all_waiting_time": 0,
        "all_waiting_time/driven_time": 0,
        "in_road_time": 5,
        "in_road_distance": 30,
        "in_road_stop_times": 0,
        "in_road_waiting_time": 0
    },
    {
        "id": 119,
        "latitude": 22.5488697269,
        "longitude": 114.078419683,
        "speed": 10,
        "driven_time": 5,
        "driven_distance": 30,
        "avg_speed": 6,
        "all_stop_times": 0,
        "all_waiting_time": 0,
        "all_waiting_time/driven_time": 0,
        "in_road_time": 5,
        "in_road_distance": 30,
        "in_road_stop_times": 0,
        "in_road_waiting_time": 0
    },
    {
        "id": 120,
        "latitude": 22.5514454077,
        "longitude": 114.076613947,
        "speed": 10,
        "driven_time": 5,
        "driven_distance": 30,
        "avg_speed": 6,
        "all_stop_times": 0,
        "all_waiting_time": 0,
        "all_waiting_time/driven_time": 0,
        "in_road_time": 5,
        "in_road_distance": 30,
        "in_road_stop_times": 0,
        "in_road_waiting_time": 0
    },
    {
        "id": 121,
        "latitude": 22.5473105787,
        "longitude": 114.087678726,
        "speed": 8,
        "driven_time": 4,
        "driven_distance": 20,
        "avg_speed": 5,
        "all_stop_times": 0,
        "all_waiting_time": 0,
        "all_waiting_time/driven_time": 0,
        "in_road_time": 4,
        "in_road_distance": 20,
        "in_road_stop_times": 0,
        "in_road_waiting_time": 0
    },
    {
        "id": 122,
        "latitude": 22.5490448334,
        "longitude": 114.079627513,
        "speed": 8,
        "driven_time": 4,
        "driven_distance": 20,
        "avg_speed": 5,
        "all_stop_times": 0,
        "all_waiting_time": 0,
        "all_waiting_time/driven_time": 0,
        "in_road_time": 4,
        "in_road_distance": 20,
        "in_road_stop_times": 0,
        "in_road_waiting_time": 0
    },
    {
        "id": 123,
        "latitude": 22.5502315819,
        "longitude": 114.07841009,
        "speed": 8,
        "driven_time": 4,
        "driven_distance": 20,
        "avg_speed": 5,
        "all_stop_times": 0,
        "all_waiting_time": 0,
        "all_waiting_time/driven_time": 0,
        "in_road_time": 4,
        "in_road_distance": 20,
        "in_road_stop_times": 0,
        "in_road_waiting_time": 0
    },
    {
        "id": 124,
        "latitude": 22.543011454,
        "longitude": 114.082419213,
        "speed": 6,
        "driven_time": 3,
        "driven_distance": 12,
        "avg_speed": 4,
        "all_stop_times": 0,
        "all_waiting_time": 0,
        "all_waiting_time/driven_time": 0,
        "in_road_time": 3,
        "in_road_distance": 12,
        "in_road_stop_times": 0,
        "in_road_waiting_time": 0
    },
    {
        "id": 125,
        "latitude": 22.5513849726,
        "longitude": 114.077361438,
        "speed": 6,
        "driven_time": 3,
        "driven_distance": 12,
        "avg_speed": 4,
        "all_stop_times": 0,
        "all_waiting_time": 0,
        "all_waiting_time/driven_time": 0,
        "in_road_time": 3,
        "in_road_distance": 12,
        "in_road_stop_times": 0,
        "in_road_waiting_time": 0
    },
    {
        "id": 126,
        "latitude": 22.550404721,
        "longitude": 114.077618009,
        "speed": 6,
        "driven_time": 3,
        "driven_distance": 12,
        "avg_speed": 4,
        "all_stop_times": 0,
        "all_waiting_time": 0,
        "all_waiting_time/driven_time": 0,
        "in_road_time": 3,
        "in_road_distance": 12,
        "in_road_stop_times": 0,
        "in_road_waiting_time": 0
    },
    {
        "id": 127,
        "latitude": 22.5513076877,
        "longitude": 114.084005868,
        "speed": 6,
        "driven_time": 3,
        "driven_distance": 12,
        "avg_speed": 4,
        "all_stop_times": 0,
        "all_waiting_time": 0,
        "all_waiting_time/driven_time": 0,
        "in_road_time": 3,
        "in_road_distance": 12,
        "in_road_stop_times": 0,
        "in_road_waiting_time": 0
    },
    {
        "id": 128,
        "latitude": 22.5512869503,
        "longitude": 114.083836767,
        "speed": 9,
        "driven_time": 3,
        "driven_distance": 18,
        "avg_speed": 6,
        "all_stop_times": 0,
        "all_waiting_time": 0,
        "all_waiting_time/driven_time": 0,
        "in_road_time": 3,
        "in_road_distance": 18,
        "in_road_stop_times": 0,
        "in_road_waiting_time": 0
    },
    {
        "id": 129,
        "latitude": 22.5452809972,
        "longitude": 114.079315865,
        "speed": 4,
        "driven_time": 2,
        "driven_distance": 6,
        "avg_speed": 3,
        "all_stop_times": 0,
        "all_waiting_time": 0,
        "all_waiting_time/driven_time": 0,
        "in_road_time": 2,
        "in_road_distance": 6,
        "in_road_stop_times": 0,
        "in_road_waiting_time": 0
    },
    {
        "id": 130,
        "latitude": 22.5457141951,
        "longitude": 114.082764521,
        "speed": 4,
        "driven_time": 2,
        "driven_distance": 6,
        "avg_speed": 3,
        "all_stop_times": 0,
        "all_waiting_time": 0,
        "all_waiting_time/driven_time": 0,
        "in_road_time": 2,
        "in_road_distance": 6,
        "in_road_stop_times": 0,
        "in_road_waiting_time": 0
    },
    {
        "id": 131,
        "latitude": 22.5471133357,
        "longitude": 114.079125161,
        "speed": 4,
        "driven_time": 2,
        "driven_distance": 6,
        "avg_speed": 3,
        "all_stop_times": 0,
        "all_waiting_time": 0,
        "all_waiting_time/driven_time": 0,
        "in_road_time": 2,
        "in_road_distance": 6,
        "in_road_stop_times": 0,
        "in_road_waiting_time": 0
    },
    {
        "id": 132,
        "latitude": 22.5470118962,
        "longitude": 114.083969426,
        "speed": 4,
        "driven_time": 2,
        "driven_distance": 6,
        "avg_speed": 3,
        "all_stop_times": 0,
        "all_waiting_time": 0,
        "all_waiting_time/driven_time": 0,
        "in_road_time": 2,
        "in_road_distance": 6,
        "in_road_stop_times": 0,
        "in_road_waiting_time": 0
    },
    {
        "id": 133,
        "latitude": 22.5516892578,
        "longitude": 114.082082355,
        "speed": 4,
        "driven_time": 2,
        "driven_distance": 6,
        "avg_speed": 3,
        "all_stop_times": 0,
        "all_waiting_time": 0,
        "all_waiting_time/driven_time": 0,
        "in_road_time": 2,
        "in_road_distance": 6,
        "in_road_stop_times": 0,
        "in_road_waiting_time": 0
    },
    {
        "id": 134,
        "latitude": 22.5472660274,
        "longitude": 114.088803902,
        "speed": 2,
        "driven_time": 1,
        "driven_distance": 2,
        "avg_speed": 2,
        "all_stop_times": 0,
        "all_waiting_time": 0,
        "all_waiting_time/driven_time": 0,
        "in_road_time": 1,
        "in_road_distance": 2,
        "in_road_stop_times": 0,
        "in_road_waiting_time": 0
    },
    {
        "id": 135,
        "latitude": 22.549201428,
        "longitude": 114.080393306,
        "speed": 2,
        "driven_time": 1,
        "driven_distance": 2,
        "avg_speed": 2,
        "all_stop_times": 0,
        "all_waiting_time": 0,
        "all_waiting_time/driven_time": 0,
        "in_road_time": 1,
        "in_road_distance": 2,
        "in_road_stop_times": 0,
        "in_road_waiting_time": 0
    }
]